{"_type":"export","__export_format":4,"__export_date":"2024-12-20T01:51:55.648Z","__export_source":"insomnia.desktop.app:v10.2.0","resources":[{"_id":"req_d88ad186af924cd6a63bc68862133a39","parentId":"wrk_13752639b84c4f75851b3a37e0e48d8c","modified":1734582800359,"created":1734475204224,"url":"http://localhost:5555/reservas/","name":"putReserva","description":"","method":"POST","body":{"mimeType":"application/json","text":"{\n\t\"dia\": \"2024-12-20T00:00:00\",\n\t\"horario\": \"16:00:00\",\n\t\"horarioFinal\": \"17:00:00\",\n\t\"duracion\": 60,\n\t\"idCancha\": 1,\n\t\"cancha\": {\n\t\t\"nombre\": \"Hercules\",\n\t\t\"techada\": true,\n\t\t\"id\": 1\n\t},\n\t\"nombreContacto\": \"\",\n\t\"telefonoContacto\": \"23\",\n\t\"id\": -1\n}"},"parameters":[],"headers":[{"name":"Content-Type","value":"application/json"},{"name":"User-Agent","value":"insomnia/10.2.0"}],"authentication":{},"metaSortKey":-1734475204224,"isPrivate":false,"pathParameters":[],"settingStoreCookies":true,"settingSendCookies":true,"settingDisableRenderRequestBody":false,"settingEncodeUrl":true,"settingRebuildPath":true,"settingFollowRedirects":"global","_type":"request"},{"_id":"wrk_13752639b84c4f75851b3a37e0e48d8c","parentId":null,"modified":1700095029901,"created":1700091474773,"name":"Clase back python 1","description":"","scope":"collection","_type":"workspace"},{"_id":"req_faa9489dd68f4b78805325f02f618f03","parentId":"fld_72d44da3e3944a7fa6fa4942fae95f00","modified":1734566018028,"created":1734565998084,"url":"http://localhost:5555/reservas/323","name":"deleteReserva","description":"","method":"DELETE","body":{},"parameters":[],"headers":[{"name":"User-Agent","value":"insomnia/10.2.0"}],"authentication":{},"metaSortKey":-1734565998084,"isPrivate":false,"pathParameters":[],"settingStoreCookies":true,"settingSendCookies":true,"settingDisableRenderRequestBody":false,"settingEncodeUrl":true,"settingRebuildPath":true,"settingFollowRedirects":"global","_type":"request"},{"_id":"fld_72d44da3e3944a7fa6fa4942fae95f00","parentId":"wrk_13752639b84c4f75851b3a37e0e48d8c","modified":1734372142741,"created":1734372142741,"name":"Final","description":"","environment":{},"environmentPropertyOrder":null,"metaSortKey":-1734372142741,"environmentType":"kv","_type":"request_group"},{"_id":"req_6c1439f323e54e179ab3d864e6a643c2","parentId":"fld_72d44da3e3944a7fa6fa4942fae95f00","modified":1734649413962,"created":1734483554343,"url":"http://localhost:5555/reservas/filtrar?dia=2024-12-10&nombre_cancha=Don+Ramon","name":"filtradoReservas","description":"http://localhost:5555/reservas/filtrar?dia=2024-12-10&nombre_cancha=Don+Ramon","method":"GET","body":{},"parameters":[],"headers":[{"name":"User-Agent","value":"insomnia/10.2.0"}],"authentication":{},"preRequestScript":"","metaSortKey":-1734483554343,"isPrivate":false,"pathParameters":[],"settingStoreCookies":true,"settingSendCookies":true,"settingDisableRenderRequestBody":false,"settingEncodeUrl":true,"settingRebuildPath":true,"settingFollowRedirects":"global","_type":"request"},{"_id":"req_d64a0863304647fd898a867bf7845eca","parentId":"fld_72d44da3e3944a7fa6fa4942fae95f00","modified":1734650685037,"created":1734376688195,"url":"http://localhost:5555/reservas/","name":"addReserva","description":"","method":"POST","body":{"mimeType":"application/json","text":"\n\t{\n\t\t\"dia\": \"2024-12-19T00:00:00\",\n\t\t\"horario\": \"18:00:00\",\n\t\t\"horarioFinal\": \"19:00:02\",\n\t\t\"duracion\": \"60\",\n\t\t\"idCancha\": 1,\n\t\t\"cancha\": {\n\t\t\t\"nombre\": \"Hercules\",\n\t\t\t\"techada\": true,\n\t\t\t\"id\": 1\n\t\t},\n\t\t\"nombreContacto\": \"Juan Pérez\",\n\t\t\"telefonoContacto\": \"344888955\",\n\t\t\"id\": 1\n\t}"},"parameters":[],"headers":[{"name":"Content-Type","value":"application/json"},{"name":"User-Agent","value":"insomnia/10.2.0"}],"authentication":{},"metaSortKey":-1734376688195,"isPrivate":false,"pathParameters":[],"settingStoreCookies":true,"settingSendCookies":true,"settingDisableRenderRequestBody":false,"settingEncodeUrl":true,"settingRebuildPath":true,"settingFollowRedirects":"global","_type":"request"},{"_id":"req_c32c3209db7f46ea95f95d089221b887","parentId":"fld_a3b6ab912ba04282855b4baca55b66f4","modified":1734479408107,"created":1734479386538,"url":"http://localhost:5555/canchas/1","name":"deleteCancha","description":"","method":"DELETE","body":{},"parameters":[],"headers":[{"name":"User-Agent","value":"insomnia/10.2.0"}],"authentication":{},"metaSortKey":-1734479386538,"isPrivate":false,"pathParameters":[],"settingStoreCookies":true,"settingSendCookies":true,"settingDisableRenderRequestBody":false,"settingEncodeUrl":true,"settingRebuildPath":true,"settingFollowRedirects":"global","_type":"request"},{"_id":"fld_a3b6ab912ba04282855b4baca55b66f4","parentId":"fld_72d44da3e3944a7fa6fa4942fae95f00","modified":1734372294562,"created":1734372294562,"name":"canchas","description":"","environment":{},"environmentPropertyOrder":null,"metaSortKey":-1734372294562,"environmentType":"kv","_type":"request_group"},{"_id":"req_b489fdcd8ffa43a9b5a9beea8289b9d0","parentId":"fld_a3b6ab912ba04282855b4baca55b66f4","modified":1734466119457,"created":1734459231066,"url":"http://localhost:5555/canchas/","name":"addCancha","description":"","method":"POST","body":{"mimeType":"application/json","text":"{\n      \"id\": \"3\",\n      \"nombre\": \"Banfield\",\n      \"techada\": true\n    }\n  "},"parameters":[],"headers":[{"name":"Content-Type","value":"application/json"},{"name":"User-Agent","value":"insomnia/10.2.0"}],"authentication":{},"metaSortKey":-1734459231066,"isPrivate":false,"pathParameters":[],"settingStoreCookies":true,"settingSendCookies":true,"settingDisableRenderRequestBody":false,"settingEncodeUrl":true,"settingRebuildPath":true,"settingFollowRedirects":"global","_type":"request"},{"_id":"req_c2bca601a6074e35a9c5950d6e073bcf","parentId":"fld_a3b6ab912ba04282855b4baca55b66f4","modified":1734459760449,"created":1734372297131,"url":"http://localhost:5555/canchas","name":"getCanchas","description":"","method":"GET","body":{},"parameters":[],"headers":[{"name":"User-Agent","value":"insomnia/10.2.0"}],"authentication":{},"metaSortKey":-1734372297131,"isPrivate":false,"pathParameters":[],"settingStoreCookies":true,"settingSendCookies":true,"settingDisableRenderRequestBody":false,"settingEncodeUrl":true,"settingRebuildPath":true,"settingFollowRedirects":"global","_type":"request"},{"_id":"req_33dda7b5d9db4befa9443ca086f8ab13","parentId":"fld_72d44da3e3944a7fa6fa4942fae95f00","modified":1734575056020,"created":1734372184166,"url":"http://localhost:5555/reservas/6","name":"getReserva","description":"","method":"GET","body":{},"parameters":[],"headers":[{"name":"User-Agent","value":"insomnia/10.2.0"}],"authentication":{},"metaSortKey":-1734372184166,"isPrivate":false,"pathParameters":[],"settingStoreCookies":true,"settingSendCookies":true,"settingDisableRenderRequestBody":false,"settingEncodeUrl":true,"settingRebuildPath":true,"settingFollowRedirects":"global","_type":"request"},{"_id":"req_01a077573a79405b88b747658df9802e","parentId":"fld_72d44da3e3944a7fa6fa4942fae95f00","modified":1734458106445,"created":1734372146995,"url":"http://localhost:5555/reservas","name":"getAllReservas","description":"","method":"GET","body":{},"parameters":[],"headers":[{"name":"User-Agent","value":"insomnia/10.2.0"}],"authentication":{},"metaSortKey":-1734372146995,"isPrivate":false,"pathParameters":[],"settingStoreCookies":true,"settingSendCookies":true,"settingDisableRenderRequestBody":false,"settingEncodeUrl":true,"settingRebuildPath":true,"settingFollowRedirects":"global","_type":"request"},{"_id":"req_bcde829413ec479c9f697048b5ffa5b3","parentId":"wrk_13752639b84c4f75851b3a37e0e48d8c","modified":1733846640794,"created":1700092977114,"url":"http://localhost:5555/moto","name":"Post Moto","description":"","method":"POST","body":{"mimeType":"application/json","text":"{\"id\":1,\"marca\":\"Yamaha\",\"cilindrada\":\"100\",\"descripcion\":\"DFASDF\"}"},"parameters":[],"headers":[{"name":"Content-Type","value":"application/json"},{"name":"User-Agent","value":"insomnia/8.4.2"}],"authentication":{},"metaSortKey":-1700092977114,"isPrivate":false,"settingStoreCookies":true,"settingSendCookies":true,"settingDisableRenderRequestBody":false,"settingEncodeUrl":true,"settingRebuildPath":true,"settingFollowRedirects":"global","_type":"request"},{"_id":"req_ed984b3c85f64eb2a6dc5fa7dfdbd24e","parentId":"wrk_13752639b84c4f75851b3a37e0e48d8c","modified":1734372077593,"created":1700093467441,"url":"http://localhost:5555/moto/1234","name":"Delete Moto","description":"","method":"DELETE","body":{"mimeType":"application/json","text":""},"parameters":[],"headers":[{"name":"Content-Type","value":"application/json"},{"name":"User-Agent","value":"insomnia/8.4.2"}],"authentication":{},"metaSortKey":-1700092762278.5,"isPrivate":false,"settingStoreCookies":true,"settingSendCookies":true,"settingDisableRenderRequestBody":false,"settingEncodeUrl":true,"settingRebuildPath":true,"settingFollowRedirects":"global","_type":"request"},{"_id":"req_92e68f74cce7462ea2a4d1336fca1588","parentId":"wrk_13752639b84c4f75851b3a37e0e48d8c","modified":1733849787787,"created":1700092547443,"url":"http://localhost:5555/moto/1","name":"PUT Moto","description":"","method":"PUT","body":{"mimeType":"application/json","text":"{\"id\":1,\"marca\":\"Yamaha\",\"cilindrada\":\"100\",\"descripcion\":\"DFASDF\"}"},"parameters":[],"headers":[{"name":"Content-Type","value":"application/json"},{"name":"User-Agent","value":"insomnia/8.4.2"}],"authentication":{},"metaSortKey":-1700092547443,"isPrivate":false,"settingStoreCookies":true,"settingSendCookies":true,"settingDisableRenderRequestBody":false,"settingEncodeUrl":true,"settingRebuildPath":true,"settingFollowRedirects":"global","_type":"request"},{"_id":"req_61a368cfbd4f47078195194190c1a14c","parentId":"wrk_13752639b84c4f75851b3a37e0e48d8c","modified":1733848233467,"created":1700092494828,"url":"http://localhost:5555/moto/2","name":"get moto","description":"","method":"GET","body":{"mimeType":"application/json","text":""},"parameters":[],"headers":[{"name":"Content-Type","value":"application/json"},{"name":"User-Agent","value":"insomnia/8.4.2"}],"authentication":{},"metaSortKey":-1700092494828,"isPrivate":false,"settingStoreCookies":true,"settingSendCookies":true,"settingDisableRenderRequestBody":false,"settingEncodeUrl":true,"settingRebuildPath":true,"settingFollowRedirects":"global","_type":"request"},{"_id":"req_4000b83d5b3f4e3f95063108a85e354c","parentId":"wrk_13752639b84c4f75851b3a37e0e48d8c","modified":1700092486704,"created":1700091485886,"url":"http://localhost:5555/motos","name":"GetAllMotos","description":"","method":"GET","body":{"mimeType":"application/json","text":"{\"id\":1, \"marca\": \"ssda\", \"cilindrada\" : 32}"},"parameters":[],"headers":[{"name":"Content-Type","value":"application/json"},{"name":"User-Agent","value":"insomnia/8.4.2"}],"authentication":{},"metaSortKey":-1700091485886,"isPrivate":false,"settingStoreCookies":true,"settingSendCookies":true,"settingDisableRenderRequestBody":false,"settingEncodeUrl":true,"settingRebuildPath":true,"settingFollowRedirects":"global","_type":"request"},{"_id":"env_1e693396259fc45113e8fca1ed6cf04fa3ffe4cb","parentId":"wrk_13752639b84c4f75851b3a37e0e48d8c","modified":1700091474774,"created":1700091474774,"name":"Base Environment","data":{},"dataPropertyOrder":null,"color":null,"isPrivate":false,"metaSortKey":1700091474774,"_type":"environment"},{"_id":"jar_1e693396259fc45113e8fca1ed6cf04fa3ffe4cb","parentId":"wrk_13752639b84c4f75851b3a37e0e48d8c","modified":1700091474775,"created":1700091474775,"name":"Default Jar","cookies":[],"_type":"cookie_jar"}]}